tradebox.py
tradeboxteste-0.0.6.dist-info/METADATA
tradeboxteste-0.0.6.dist-info/WHEEL
tradeboxteste-0.0.6.dist-info/top_level.txt
tradeboxteste-0.0.6.dist-info/RECORD
