Metadata-Version: 2.1
Name: tradeboxteste
Version: 0.0.6
Summary: Teste
Home-page: UNKNOWN
Author: UNKNOWN
Author-email: UNKNOWN
License: UNKNOWN
Platform: UNKNOWN
